scistyles/__init__.py
scistyles/core.py
scistyles/stylelib/ACS_nano-hs.mplstyle
scistyles/stylelib/PRL-hs.mplstyle
scistyles/stylelib/apl-sp.mplstyle
scistyles/stylelib/aps_sans-hs.mplstyle
scistyles/stylelib/nature_com-hs.mplstyle
scistyles/stylelib/optlett-sp.mplstyle
scistyles/stylelib/pnas-sp.mplstyle
scistyles/stylelib/presentation-sp.mplstyle
scistyles-1.0.dist-info/LICENSE
scistyles-1.0.dist-info/WHEEL
scistyles-1.0.dist-info/METADATA
scistyles-1.0.dist-info/RECORD
