Metadata-Version: 2.1
Name: scistyles
Version: 1.0
Summary: scistyles: Matplotlib stylesheets for scientific publications.
Author: Samuel Palato
Classifier: License :: OSI Approved :: MIT License
Classifier: Framework :: Matplotlib
Classifier: Intended Audience :: Science/Research
Classifier: Programming Language :: Python :: 3
Classifier: Topic :: Scientific/Engineering :: Visualization
Classifier: License :: OSI Approved :: MIT License
Requires-Dist: matplotlib
Requires-Dist: pytest ; extra == "dev"
Requires-Dist: numpy ; extra == "dev"
Requires-Dist: flit ; extra == "dev"
Project-URL: Source, https://github.com/spalato/scistyles
Provides-Extra: dev
